foxlin/__init__.py
foxlin/api/__init__.py
foxlin/cli/__init__.py
foxlin/client/__init__.py
foxlin/core/__init__.py
foxlin/core/box/__init__.py
foxlin/core/box/fox.py
foxlin/core/box/log.py
foxlin/core/box/memory.py
foxlin/core/box/storage.py
foxlin/core/column.py
foxlin/core/den.py
foxlin/core/error.py
foxlin/core/fox.py
foxlin/core/query.py
foxlin/core/sophy.py
foxlin/errors/__init__.py
foxlin/errors/base.py
foxlin/errors/memory.py
foxlin/errors/record.py
foxlin/errors/storage.py
foxlin/utils/__init__.py
foxlin/utils/id_generator.py
foxlin/utils/utils.py
foxlin-0.1.2.dist-info/LICENSE
foxlin-0.1.2.dist-info/METADATA
foxlin-0.1.2.dist-info/WHEEL
foxlin-0.1.2.dist-info/RECORD
