Metadata-Version: 2.1
Name: foxlin
Version: 0.1.2
Summary: simple, fast memory-based DBMS
Author: misano
Author-email: me@MirSobhan.ir
Requires-Python: >=3.9,<3.11
Classifier: Programming Language :: Python :: 3
Classifier: Programming Language :: Python :: 3.9
Classifier: Programming Language :: Python :: 3.10
Requires-Dist: numpy (>=2.0.0,<3.0.0)
Requires-Dist: orjson (>=3.10.6,<4.0.0)
Requires-Dist: pydantic (==1.10.7)
